mcp_zephyr_scale_cloud/__init__.py
mcp_zephyr_scale_cloud/clients/__init__.py
mcp_zephyr_scale_cloud/clients/zephyr_client.py
mcp_zephyr_scale_cloud/config.py
mcp_zephyr_scale_cloud/schemas/__init__.py
mcp_zephyr_scale_cloud/schemas/base.py
mcp_zephyr_scale_cloud/schemas/common.py
mcp_zephyr_scale_cloud/schemas/folder.py
mcp_zephyr_scale_cloud/schemas/priority.py
mcp_zephyr_scale_cloud/schemas/project.py
mcp_zephyr_scale_cloud/schemas/status.py
mcp_zephyr_scale_cloud/schemas/test_case.py
mcp_zephyr_scale_cloud/schemas/test_cycle.py
mcp_zephyr_scale_cloud/schemas/test_plan.py
mcp_zephyr_scale_cloud/schemas/test_script.py
mcp_zephyr_scale_cloud/schemas/test_step.py
mcp_zephyr_scale_cloud/schemas/version.py
mcp_zephyr_scale_cloud/server.py
mcp_zephyr_scale_cloud/utils/__init__.py
mcp_zephyr_scale_cloud/utils/validation.py
mcp_zephyr_scale_cloud-0.1.8.dist-info/METADATA
mcp_zephyr_scale_cloud-0.1.8.dist-info/WHEEL
mcp_zephyr_scale_cloud-0.1.8.dist-info/entry_points.txt
mcp_zephyr_scale_cloud-0.1.8.dist-info/licenses/LICENSE
mcp_zephyr_scale_cloud-0.1.8.dist-info/RECORD
