Metadata-Version: 2.4
Name: mcp-zephyr-scale-cloud
Version: 0.1.8
Summary: Model Context Protocol server for Zephyr Scale Cloud
License-File: LICENSE
Keywords: mcp,zephyr,scale,testing,jira
Author: Yevhen Burlaka
Author-email: yevhen.burlaka@example.com
Requires-Python: >=3.10
Classifier: Development Status :: 3 - Alpha
Classifier: Intended Audience :: Developers
Classifier: License :: OSI Approved :: MIT License
Classifier: Programming Language :: Python :: 3
Classifier: Programming Language :: Python :: 3.10
Classifier: Programming Language :: Python :: 3.11
Classifier: Programming Language :: Python :: 3.12
Classifier: Programming Language :: Python :: 3.13
Provides-Extra: dev
Requires-Dist: black (>=25.1.0) ; extra == "dev"
Requires-Dist: httpx (>=0.28.1)
Requires-Dist: isort (>=6.0.0) ; extra == "dev"
Requires-Dist: mcp (>=1.0.0)
Requires-Dist: mypy (>=1.17.0) ; extra == "dev"
Requires-Dist: pydantic (>=2.11.7)
Requires-Dist: pytest (>=8.4.0) ; extra == "dev"
Requires-Dist: pytest-asyncio (>=1.1.0) ; extra == "dev"
Requires-Dist: pytest-httpx (>=0.35.0) ; extra == "dev"
Requires-Dist: python-dotenv (>=1.0.0)
Requires-Dist: ruff (>=0.12.0) ; extra == "dev"
Project-URL: Homepage, https://github.com/basterboy/mcp-zephyr-scale-cloud
Project-URL: Issues, https://github.com/basterboy/mcp-zephyr-scale-cloud/issues
Project-URL: Repository, https://github.com/basterboy/mcp-zephyr-scale-cloud
